odoo9_addon_account_payment_sale-9.0.1.0.0.99.dev26-py2.7-nspkg.pth
odoo9_addon_account_payment_sale-9.0.1.0.0.99.dev26.dist-info/DESCRIPTION.rst
odoo9_addon_account_payment_sale-9.0.1.0.0.99.dev26.dist-info/METADATA
odoo9_addon_account_payment_sale-9.0.1.0.0.99.dev26.dist-info/RECORD
odoo9_addon_account_payment_sale-9.0.1.0.0.99.dev26.dist-info/WHEEL
odoo9_addon_account_payment_sale-9.0.1.0.0.99.dev26.dist-info/metadata.json
odoo9_addon_account_payment_sale-9.0.1.0.0.99.dev26.dist-info/namespace_packages.txt
odoo9_addon_account_payment_sale-9.0.1.0.0.99.dev26.dist-info/top_level.txt
odoo_addons/account_payment_sale/README.rst
odoo_addons/account_payment_sale/__init__.py
odoo_addons/account_payment_sale/__openerp__.py
odoo_addons/account_payment_sale/i18n/account_payment_sale.pot
odoo_addons/account_payment_sale/i18n/ca.po
odoo_addons/account_payment_sale/i18n/de.po
odoo_addons/account_payment_sale/i18n/el_GR.po
odoo_addons/account_payment_sale/i18n/es.po
odoo_addons/account_payment_sale/i18n/es_ES.po
odoo_addons/account_payment_sale/i18n/es_VE.po
odoo_addons/account_payment_sale/i18n/fi.po
odoo_addons/account_payment_sale/i18n/fr.po
odoo_addons/account_payment_sale/i18n/gl.po
odoo_addons/account_payment_sale/i18n/hr.po
odoo_addons/account_payment_sale/i18n/hr_HR.po
odoo_addons/account_payment_sale/i18n/hu.po
odoo_addons/account_payment_sale/i18n/it.po
odoo_addons/account_payment_sale/i18n/nl.po
odoo_addons/account_payment_sale/i18n/nl_NL.po
odoo_addons/account_payment_sale/i18n/pt.po
odoo_addons/account_payment_sale/i18n/pt_BR.po
odoo_addons/account_payment_sale/i18n/ro.po
odoo_addons/account_payment_sale/i18n/sk.po
odoo_addons/account_payment_sale/i18n/sl.po
odoo_addons/account_payment_sale/i18n/tr.po
odoo_addons/account_payment_sale/i18n/tr_TR.po
odoo_addons/account_payment_sale/i18n/vi_VN.po
odoo_addons/account_payment_sale/i18n/zh_CN.po
odoo_addons/account_payment_sale/models/__init__.py
odoo_addons/account_payment_sale/models/sale_order.py
odoo_addons/account_payment_sale/static/description/icon.png
odoo_addons/account_payment_sale/views/sale_order_view.xml
odoo_addons/account_payment_sale/wizard/__init__.py
odoo_addons/account_payment_sale/wizard/sale_make_invoice_advance.py
